{
    "dashboards": [
        {
            "uri": "https://grafana.tools.test.io/dashboard/",
            "duration": 6000
        },
        {
            "uri": "https://grafana.tools.test.io/dashboard2",
            "duration": 10000
        },
        {
            "uri": "https://plainhtml.io/team_focus",
            "duration": 10000,
            "type": "html"
        }
    ],
    "requestEnhancements": [
        {
            "patterns": ["https://grafana.tools.test.io/*"],
            "headers": {
                "Authorization": "Bearer iambeareroftoken"
            }
        }
    ]
}
